{
    "output directory":"../mesh/cnt_mesh_fiber_4000_exp",
    "keep old files":false,

    "visualize":false,
    
    "container width [nm]":400,

    "drop height [nm]": 20,

    "number of chirality": 1,
    "cnt chirality": [4,2],
    "cnt diameter [nm]":0.5,
    "cnt total length [nm]": [200,200],
    "cnt section length [nm]": [5,20],

    "number of tubes added together": 5,
    "number of active bundles": 40,
    "number of tubes before deletion": 10000,
    "number of unsaved tubes": 300,
    "number of bundles": 300,
    "number_of_steps": 10,
    "time_step": 0.05

}
